{
  "version": "2.6.2",
  "summary": {
    "title": "New Threat Model",
    "owner": "",
    "description": "",
    "id": 0
  },
  "detail": {
    "contributors": [],
    "diagrams": [
      {
        "id": 0,
        "title": "New STRIDE diagram",
        "diagramType": "STRIDE",
        "placeholder": "New STRIDE diagram description",
        "thumbnail": "./public/content/images/thumbnail.stride.jpg",
        "version": "2.6.2",
        "cells": [
          {
            "position": {
              "x": 140,
              "y": 260
            },
            "size": {
              "width": 60,
              "height": 60
            },
            "attrs": {
              "body": {
                "stroke": "#333333",
                "strokeWidth": 1.5,
                "strokeDasharray": null
              }
            },
            "visible": true,
            "shape": "process",
            "ports": {
              "groups": {
                "top": {
                  "position": "top",
                  "attrs": {
                    "circle": {
                      "r": 4,
                      "magnet": true,
                      "stroke": "#5F95FF",
                      "strokeWidth": 1,
                      "fill": "#fff",
                      "style": {
                        "visibility": "hidden"
                      }
                    }
                  }
                },
                "right": {
                  "position": "right",
                  "attrs": {
                    "circle": {
                      "r": 4,
                      "magnet": true,
                      "stroke": "#5F95FF",
                      "strokeWidth": 1,
                      "fill": "#fff",
                      "style": {
                        "visibility": "hidden"
                      }
                    }
                  }
                },
                "bottom": {
                  "position": "bottom",
                  "attrs": {
                    "circle": {
                      "r": 4,
                      "magnet": true,
                      "stroke": "#5F95FF",
                      "strokeWidth": 1,
                      "fill": "#fff",
                      "style": {
                        "visibility": "hidden"
                      }
                    }
                  }
                },
                "left": {
                  "position": "left",
                  "attrs": {
                    "circle": {
                      "r": 4,
                      "magnet": true,
                      "stroke": "#5F95FF",
                      "strokeWidth": 1,
                      "fill": "#fff",
                      "style": {
                        "visibility": "hidden"
                      }
                    }
                  }
                }
              },
              "items": [
                {
                  "group": "top",
                  "id": "a889ae93-ee51-47f4-a938-d3c2d5e66557"
                },
                {
                  "group": "right",
                  "id": "7dc0179a-0628-4d6b-99a4-38b6a754c264"
                },
                {
                  "group": "bottom",
                  "id": "b00b3f1f-4014-4827-b1c5-e30b960e0f7a"
                },
                {
                  "group": "left",
                  "id": "991a2cf5-f625-4f7f-8a62-9371288a70b4"
                }
              ]
            },
            "id": "7bf77f47-32ed-4810-923c-8e75fbcb9732",
            "zIndex": 1,
            "data": {
              "type": "tm.Process",
              "name": "Process",
              "description": "",
              "outOfScope": false,
              "isTrustBoundary": false,
              "reasonOutOfScope": "",
              "hasOpenThreats": false,
              "handlesCardPayment": false,
              "handlesGoodsOrServices": false,
              "isWebApplication": false,
              "privilegeLevel": "",
              "threats": []
            }
          }
        ]
      }
    ],
    "diagramTop": 1,
    "reviewer": "",
    "threatTop": 0
  }
}